{
  "toc": {
    "sections": [
      {
        "title": "Start",
        "source": "docs/README.md",
        "url": "index.html",
        "slug": "index"
      },
      {
        "title": "Ideologi",
        "source": "docs/ideologi.md",
        "url": "ideologi.html",
        "slug": "ideologi"
      },
      {
        "title": "Byteshandlar",
        "source": "docs/byteshandlar.md",
        "url": "byteshandlar.html",
        "slug": "byteshandlar",
        "headings": [
          {
            "title": "Hur det går till",
            "depth": 2,
            "id": "hur-det-gar-till"
          },
          {
            "title": "[Binance](https://www.binance.com/)",
            "depth": 2,
            "id": "binance(https:www.binance.com)"
          },
          {
            "title": "[CoinBase](https://www.coinbase.com/)",
            "depth": 2,
            "id": "coinbase(https:www.coinbase.com)"
          },
          {
            "title": "[KuCoin](https://www.kucoin.com/)",
            "depth": 2,
            "id": "kucoin(https:www.kucoin.com)"
          },
          {
            "title": "Fler byteshandlare",
            "depth": 2,
            "id": "fler-byteshandlare"
          }
        ]
      },
      {
        "title": "Plånböcker",
        "source": "docs/planbocker.md",
        "url": "planbocker.html",
        "slug": "planbocker",
        "headings": [
          {
            "title": "Säkerhet",
            "depth": 2,
            "id": "sakerhet"
          }
        ]
      },
      {
        "title": "Trading",
        "source": "docs/trading.md",
        "url": "trading.html",
        "slug": "trading",
        "headings": [
          {
            "title": "Portfölj",
            "depth": 2,
            "id": "portfolj"
          }
        ]
      },
      {
        "title": "Skatt",
        "source": "docs/skatt.md",
        "url": "skatt.html",
        "slug": "skatt"
      },
      {
        "title": "Sociala nätverk",
        "source": "docs/sociala-natverk.md",
        "url": "sociala-natverk.html",
        "slug": "sociala-natverk"
      },
      {
        "title": "Terminologi",
        "source": "docs/terminologi.md",
        "url": "terminologi.html",
        "slug": "terminologi"
      },
      {
        "title": "Tekniker",
        "sections": [
          {
            "title": "Blockkedjor",
            "source": "docs/tekniker/blockkedjor.md",
            "url": "tekniker/blockkedjor.html",
            "slug": "teknikerblockkedjor"
          },
          {
            "title": "Riktad acyklisk graf (DAG)",
            "source": "docs/tekniker/riktad-acyklisk-graf.md",
            "url": "tekniker/riktad-acyklisk-graf.html",
            "slug": "teknikerriktad-acyklisk-graf"
          },
          {
            "title": "Hashgrafer",
            "source": "docs/tekniker/hashgrafer.md",
            "url": "tekniker/hashgrafer.html",
            "slug": "teknikerhashgrafer"
          },
          {
            "title": "Smarta kontrakt",
            "source": "docs/tekniker/smarta-kontrakt.md",
            "url": "tekniker/smarta-kontrakt.html",
            "slug": "teknikersmarta-kontrakt"
          }
        ]
      },
      {
        "title": "Kryptovalutor",
        "sections": [
          {
            "title": "Bitcoin",
            "source": "docs/kryptovalutor/bitcoin.md",
            "url": "kryptovalutor/bitcoin.html",
            "slug": "kryptovalutorbitcoin"
          },
          {
            "title": "Ethereum",
            "source": "docs/kryptovalutor/ethereum.md",
            "url": "kryptovalutor/ethereum.html",
            "slug": "kryptovalutorethereum"
          },
          {
            "title": "XRP",
            "source": "docs/kryptovalutor/xrp.md",
            "url": "kryptovalutor/xrp.html",
            "slug": "kryptovalutorxrp"
          },
          {
            "title": "TRON",
            "source": "docs/kryptovalutor/tron.md",
            "url": "kryptovalutor/tron.html",
            "slug": "kryptovalutortron"
          },
          {
            "title": "Stellar",
            "source": "docs/kryptovalutor/stellar.md",
            "url": "kryptovalutor/stellar.html",
            "slug": "kryptovalutorstellar"
          },
          {
            "title": "Cardano",
            "source": "docs/kryptovalutor/cardano.md",
            "url": "kryptovalutor/cardano.html",
            "slug": "kryptovalutorcardano"
          },
          {
            "title": "Monero",
            "source": "docs/kryptovalutor/monero.md",
            "url": "kryptovalutor/monero.html",
            "slug": "kryptovalutormonero"
          },
          {
            "title": "IOTA",
            "source": "docs/kryptovalutor/iota.md",
            "url": "kryptovalutor/iota.html",
            "slug": "kryptovalutoriota"
          },
          {
            "title": "NEO",
            "source": "docs/kryptovalutor/neo.md",
            "url": "kryptovalutor/neo.html",
            "slug": "kryptovalutorneo"
          },
          {
            "title": "VeChain",
            "source": "docs/kryptovalutor/vechain.md",
            "url": "kryptovalutor/vechain.html",
            "slug": "kryptovalutorvechain"
          }
        ]
      },
      {
        "title": "Ytterligare information",
        "source": "docs/ytterligare-information.md",
        "url": "ytterligare-information.html",
        "slug": "ytterligare-information"
      },
      {
        "title": "Donationer",
        "source": "docs/donationer.md",
        "url": "donationer.html",
        "slug": "donationer"
      }
    ]
  },
  "index": {
    "index.html": {
      "source": "docs/README.md",
      "title": "Start",
      "pageTitle": "Start",
      "slug": "index"
    },
    "ideologi.html": {
      "source": "docs/ideologi.md",
      "title": "Ideologi - Start",
      "pageTitle": "Ideologi",
      "slug": "ideologi"
    },
    "byteshandlar.html": {
      "source": "docs/byteshandlar.md",
      "title": "Byteshandlar - Start",
      "pageTitle": "Byteshandlar",
      "slug": "byteshandlar",
      "headings": [
        {
          "title": "Hur det går till",
          "depth": 2,
          "id": "hur-det-gar-till"
        },
        {
          "title": "[Binance](https://www.binance.com/)",
          "depth": 2,
          "id": "binance(https:www.binance.com)"
        },
        {
          "title": "[CoinBase](https://www.coinbase.com/)",
          "depth": 2,
          "id": "coinbase(https:www.coinbase.com)"
        },
        {
          "title": "[KuCoin](https://www.kucoin.com/)",
          "depth": 2,
          "id": "kucoin(https:www.kucoin.com)"
        },
        {
          "title": "Fler byteshandlare",
          "depth": 2,
          "id": "fler-byteshandlare"
        }
      ]
    },
    "planbocker.html": {
      "source": "docs/planbocker.md",
      "title": "Plånböcker - Start",
      "pageTitle": "Plånböcker",
      "slug": "planbocker",
      "headings": [
        {
          "title": "Säkerhet",
          "depth": 2,
          "id": "sakerhet"
        }
      ]
    },
    "trading.html": {
      "source": "docs/trading.md",
      "title": "Trading - Start",
      "pageTitle": "Trading",
      "slug": "trading",
      "headings": [
        {
          "title": "Portfölj",
          "depth": 2,
          "id": "portfolj"
        }
      ]
    },
    "skatt.html": {
      "source": "docs/skatt.md",
      "title": "Skatt - Start",
      "pageTitle": "Skatt",
      "slug": "skatt"
    },
    "sociala-natverk.html": {
      "source": "docs/sociala-natverk.md",
      "title": "Sociala nätverk - Start",
      "pageTitle": "Sociala nätverk",
      "slug": "sociala-natverk"
    },
    "terminologi.html": {
      "source": "docs/terminologi.md",
      "title": "Terminologi - Start",
      "pageTitle": "Terminologi",
      "slug": "terminologi"
    },
    "tekniker/blockkedjor.html": {
      "source": "docs/tekniker/blockkedjor.md",
      "title": "Blockkedjor - Start",
      "pageTitle": "Blockkedjor",
      "slug": "teknikerblockkedjor"
    },
    "tekniker/riktad-acyklisk-graf.html": {
      "source": "docs/tekniker/riktad-acyklisk-graf.md",
      "title": "Riktad acyklisk graf (DAG) - Start",
      "pageTitle": "Riktad acyklisk graf (DAG)",
      "slug": "teknikerriktad-acyklisk-graf"
    },
    "tekniker/hashgrafer.html": {
      "source": "docs/tekniker/hashgrafer.md",
      "title": "Hashgrafer - Start",
      "pageTitle": "Hashgrafer",
      "slug": "teknikerhashgrafer"
    },
    "tekniker/smarta-kontrakt.html": {
      "source": "docs/tekniker/smarta-kontrakt.md",
      "title": "Smarta kontrakt - Start",
      "pageTitle": "Smarta kontrakt",
      "slug": "teknikersmarta-kontrakt"
    },
    "kryptovalutor/bitcoin.html": {
      "source": "docs/kryptovalutor/bitcoin.md",
      "title": "Bitcoin - Start",
      "pageTitle": "Bitcoin",
      "slug": "kryptovalutorbitcoin"
    },
    "kryptovalutor/ethereum.html": {
      "source": "docs/kryptovalutor/ethereum.md",
      "title": "Ethereum - Start",
      "pageTitle": "Ethereum",
      "slug": "kryptovalutorethereum"
    },
    "kryptovalutor/xrp.html": {
      "source": "docs/kryptovalutor/xrp.md",
      "title": "XRP - Start",
      "pageTitle": "XRP",
      "slug": "kryptovalutorxrp"
    },
    "kryptovalutor/tron.html": {
      "source": "docs/kryptovalutor/tron.md",
      "title": "TRON - Start",
      "pageTitle": "TRON",
      "slug": "kryptovalutortron"
    },
    "kryptovalutor/stellar.html": {
      "source": "docs/kryptovalutor/stellar.md",
      "title": "Stellar - Start",
      "pageTitle": "Stellar",
      "slug": "kryptovalutorstellar"
    },
    "kryptovalutor/cardano.html": {
      "source": "docs/kryptovalutor/cardano.md",
      "title": "Cardano - Start",
      "pageTitle": "Cardano",
      "slug": "kryptovalutorcardano"
    },
    "kryptovalutor/monero.html": {
      "source": "docs/kryptovalutor/monero.md",
      "title": "Monero - Start",
      "pageTitle": "Monero",
      "slug": "kryptovalutormonero"
    },
    "kryptovalutor/iota.html": {
      "source": "docs/kryptovalutor/iota.md",
      "title": "IOTA - Start",
      "pageTitle": "IOTA",
      "slug": "kryptovalutoriota"
    },
    "kryptovalutor/neo.html": {
      "source": "docs/kryptovalutor/neo.md",
      "title": "NEO - Start",
      "pageTitle": "NEO",
      "slug": "kryptovalutorneo"
    },
    "kryptovalutor/vechain.html": {
      "source": "docs/kryptovalutor/vechain.md",
      "title": "VeChain - Start",
      "pageTitle": "VeChain",
      "slug": "kryptovalutorvechain"
    },
    "ytterligare-information.html": {
      "source": "docs/ytterligare-information.md",
      "title": "Ytterligare information - Start",
      "pageTitle": "Ytterligare information",
      "slug": "ytterligare-information"
    },
    "donationer.html": {
      "source": "docs/donationer.md",
      "title": "Donationer - Start",
      "pageTitle": "Donationer",
      "slug": "donationer"
    }
  },
  "sources": {
    "docs/README.md": "index.html",
    "docs/ideologi.md": "ideologi.html",
    "docs/byteshandlar.md": "byteshandlar.html",
    "docs/planbocker.md": "planbocker.html",
    "docs/trading.md": "trading.html",
    "docs/skatt.md": "skatt.html",
    "docs/sociala-natverk.md": "sociala-natverk.html",
    "docs/terminologi.md": "terminologi.html",
    "docs/tekniker/blockkedjor.md": "tekniker/blockkedjor.html",
    "docs/tekniker/riktad-acyklisk-graf.md": "tekniker/riktad-acyklisk-graf.html",
    "docs/tekniker/hashgrafer.md": "tekniker/hashgrafer.html",
    "docs/tekniker/smarta-kontrakt.md": "tekniker/smarta-kontrakt.html",
    "docs/kryptovalutor/bitcoin.md": "kryptovalutor/bitcoin.html",
    "docs/kryptovalutor/ethereum.md": "kryptovalutor/ethereum.html",
    "docs/kryptovalutor/xrp.md": "kryptovalutor/xrp.html",
    "docs/kryptovalutor/tron.md": "kryptovalutor/tron.html",
    "docs/kryptovalutor/stellar.md": "kryptovalutor/stellar.html",
    "docs/kryptovalutor/cardano.md": "kryptovalutor/cardano.html",
    "docs/kryptovalutor/monero.md": "kryptovalutor/monero.html",
    "docs/kryptovalutor/iota.md": "kryptovalutor/iota.html",
    "docs/kryptovalutor/neo.md": "kryptovalutor/neo.html",
    "docs/kryptovalutor/vechain.md": "kryptovalutor/vechain.html",
    "docs/ytterligare-information.md": "ytterligare-information.html",
    "docs/donationer.md": "donationer.html",
    "docs/styles.css": "styles.css"
  }
}
